LICENSE.txt
README.rst
setup.cfg
setup.py
src/AppTools/Boxes.py
src/AppTools/ConfusionMatrices.py
src/AppTools/Coords.py
src/AppTools/CurrentRenderer.py
src/AppTools/Displays.py
src/AppTools/Meters.py
src/AppTools/ParallelPort.py
src/AppTools/Shapes.py
src/AppTools/StateMonitors.py
src/AppTools/StimulusQueue.py
src/AppTools/__init__.py
src/BCI2000Tools/AudioSourceModule.py
src/BCI2000Tools/Chain.py
src/BCI2000Tools/Classification.py
src/BCI2000Tools/DataFiles.py
src/BCI2000Tools/Expressions.py
src/BCI2000Tools/FileReader.py
src/BCI2000Tools/LoadStream2Mat.py
src/BCI2000Tools/NIASourceModule.py
src/BCI2000Tools/Parameters.py
src/BCI2000Tools/PlaybackSourceModule.py
src/BCI2000Tools/SpellerTools.py
src/BCI2000Tools/TimingAnalysis.py
src/BCI2000Tools/__init__.py
src/BCPy2000.egg-info/PKG-INFO
src/BCPy2000.egg-info/SOURCES.txt
src/BCPy2000.egg-info/dependency_links.txt
src/BCPy2000.egg-info/requires.txt
src/BCPy2000.egg-info/top_level.txt
src/Documentation/__init__.py
src/LangTools/ModelTesting.py
src/LangTools/ProgressMonitoring.py
src/LangTools/TextPrediction.py
src/LangTools/TreeStructure.py
src/LangTools/__init__.py
src/SigTools/Basic.py
src/SigTools/Buffering.py
src/SigTools/Buffering4417.py
src/SigTools/ElectrodeGrids.py
src/SigTools/ElectrodePositions.py
src/SigTools/Electrodes.py
src/SigTools/Filtering.py
src/SigTools/LearningTools.py
src/SigTools/NumTools.py
src/SigTools/Optimization.py
src/SigTools/Plotting.py
src/SigTools/Stimuli.py
src/SigTools/__init__.py
src/SigTools/klr.py
src/WavTools/Background.py
src/WavTools/Base.py
src/WavTools/FakePyGame.py
src/WavTools/MasterVolume.py
src/WavTools/Modulate.py
src/WavTools/Plotting.py
src/WavTools/PyAudioInterface.py
src/WavTools/WavFiles.py
src/WavTools/__init__.py